README.rst
cssdecl.py
setup.cfg
setup.py
cssdecl.egg-info/PKG-INFO
cssdecl.egg-info/SOURCES.txt
cssdecl.egg-info/dependency_links.txt
cssdecl.egg-info/top_level.txt