Metadata-Version: 1.1
Name: cssdecl
Version: 0.1.2
Summary: Python CSS declaration computer
Home-page: https://github.com/jnothman/cssdecl
Author: Joel Nothman
Author-email: joel.nothman@gmail.com
License: BSD 3-Clause License
Platform: UNKNOWN
Classifier: Programming Language :: Python :: 2
Classifier: Programming Language :: Python :: 2.7
Classifier: Programming Language :: Python :: 3
Classifier: Programming Language :: Python :: 3.5
Classifier: Programming Language :: Python :: 3.6
